demo.py
main.py
analyzers/__init__.py
analyzers/market_regime_analyzer.py
analyzers/risk_manager.py
analyzers/scheduler.py
analyzers/sector_filter.py
analyzers/stock_picker.py
analyzers/workflow.py
config/__init__.py
config/settings.py
kis_api/__init__.py
kis_api/client.py
models/__init__.py
models/data_models.py
utils/__init__.py
utils/error_handling.py
utils/logging.py
lsmr_stock_picker-1.0.4.dist-info/METADATA
lsmr_stock_picker-1.0.4.dist-info/WHEEL
lsmr_stock_picker-1.0.4.dist-info/entry_points.txt
lsmr_stock_picker-1.0.4.dist-info/top_level.txt
lsmr_stock_picker-1.0.4.dist-info/RECORD
