Metadata-Version: 2.4
Name: lsmr-stock-picker
Version: 1.0.4
Summary: Leading Sector Mean Reversion 주식 선택 시스템
Author-email: LSMR Trading System <admin@lsmr.com>
License: MIT
Project-URL: Homepage, https://github.com/lsmr/stock-picker
Project-URL: Repository, https://github.com/lsmr/stock-picker.git
Project-URL: Issues, https://github.com/lsmr/stock-picker/issues
Classifier: Development Status :: 4 - Beta
Classifier: Intended Audience :: Financial and Insurance Industry
Classifier: License :: OSI Approved :: MIT License
Classifier: Programming Language :: Python :: 3
Classifier: Programming Language :: Python :: 3.9
Classifier: Programming Language :: Python :: 3.10
Classifier: Programming Language :: Python :: 3.11
Classifier: Topic :: Office/Business :: Financial :: Investment
Requires-Python: >=3.9
Requires-Dist: fastapi>=0.104.1
Requires-Dist: uvicorn[standard]>=0.24.0
Requires-Dist: websockets>=12.0
Requires-Dist: aiohttp>=3.9.1
Requires-Dist: requests>=2.31.0
Requires-Dist: pandas>=2.1.4
Requires-Dist: numpy>=1.24.4
Requires-Dist: asyncio-mqtt>=0.16.1
Requires-Dist: python-dotenv>=1.0.0
Requires-Dist: pydantic>=2.5.2
Requires-Dist: pydantic-settings>=2.1.0
Requires-Dist: structlog>=23.2.0
Requires-Dist: psutil>=5.9.6
Requires-Dist: python-dateutil>=2.8.2
Requires-Dist: orjson>=3.9.10
Requires-Dist: psycopg2-binary>=2.9.9
Requires-Dist: sqlalchemy>=2.0.23
Requires-Dist: asyncpg>=0.29.0
Provides-Extra: dev
Requires-Dist: pytest>=7.4.3; extra == "dev"
Requires-Dist: pytest-asyncio>=0.21.1; extra == "dev"
Requires-Dist: pytest-cov>=4.1.0; extra == "dev"
Requires-Dist: hypothesis>=6.92.1; extra == "dev"
Requires-Dist: black>=23.12.0; extra == "dev"
Requires-Dist: flake8>=6.1.0; extra == "dev"
Requires-Dist: mypy>=1.7.1; extra == "dev"
